server.py
atlassian_jira_mcp_server-1.0.0.dist-info/licenses/LICENSE
modules/__init__.py
modules/prompts/__init__.py
modules/prompts/prompts.py
modules/registries/__init__.py
modules/registries/resource_registry.py
modules/registries/tool_registry.py
modules/resources/__init__.py
modules/resources/resources.py
modules/tools/__init__.py
modules/tools/tools.py
modules/utilities/__init__.py
modules/utilities/adf_utils.py
modules/utilities/component_resolver.py
modules/utilities/transition_resolver.py
utils/__init__.py
utils/api_client.py
utils/auth.py
utils/config.py
atlassian_jira_mcp_server-1.0.0.dist-info/METADATA
atlassian_jira_mcp_server-1.0.0.dist-info/WHEEL
atlassian_jira_mcp_server-1.0.0.dist-info/entry_points.txt
atlassian_jira_mcp_server-1.0.0.dist-info/top_level.txt
atlassian_jira_mcp_server-1.0.0.dist-info/RECORD
