Metadata-Version: 2.4
Name: atlassian-jira-mcp-server
Version: 1.0.0
Summary: Jira MCP (Model Context Protocol) server built with FastMCP for Jira Cloud API v3
Author-email: Jason Schulz <jason@schulz.studio>
License: MIT
Project-URL: Homepage, https://github.com/your-username/atlassian-jira-mcp-server
Project-URL: Repository, https://github.com/your-username/atlassian-jira-mcp-server
Project-URL: Issues, https://github.com/your-username/atlassian-jira-mcp-server/issues
Keywords: mcp,jira,api,fastmcp,model-context-protocol,atlassian
Classifier: Development Status :: 4 - Beta
Classifier: Intended Audience :: Developers
Classifier: License :: OSI Approved :: MIT License
Classifier: Operating System :: OS Independent
Classifier: Programming Language :: Python :: 3
Classifier: Programming Language :: Python :: 3.10
Classifier: Programming Language :: Python :: 3.11
Classifier: Programming Language :: Python :: 3.12
Classifier: Topic :: Software Development :: Libraries :: Python Modules
Classifier: Topic :: Internet :: WWW/HTTP :: Dynamic Content
Requires-Python: >=3.10
License-File: LICENSE
Requires-Dist: fastmcp>=2.12.1
Requires-Dist: httpx>=0.25.0
Requires-Dist: python-dotenv>=1.0.0
Requires-Dist: adf-lib>=0.2.0
Dynamic: license-file
